prefect_supporter/__init__.py
prefect_supporter/flow/__init__.py
prefect_supporter/flow/clear_db_history.py
prefect_supporter/model/__init__.py
prefect_supporter/model/clearing_db.py
prefect_supporter-1.0.4.dist-info/METADATA
prefect_supporter-1.0.4.dist-info/WHEEL
prefect_supporter-1.0.4.dist-info/RECORD
