Metadata-Version: 2.1
Name: prefect-supporter
Version: 1.0.4
Summary: Prefect Supporter
Home-page: https://github.com/ultimatelife/prefect-supporter
License: MIT
Keywords: prefect,prefect-supporter
Author: Kunizno
Author-email: pykunzino@gmail.com
Maintainer: Kunizno
Maintainer-email: pykunzino@gmail.com
Requires-Python: >=3.9,<4.0
Classifier: Intended Audience :: Developers
Classifier: License :: OSI Approved :: MIT License
Classifier: Operating System :: OS Independent
Classifier: Programming Language :: Python :: 3
Classifier: Programming Language :: Python :: 3.9
Classifier: Programming Language :: Python :: 3.10
Classifier: Programming Language :: Python :: 3.11
Classifier: Programming Language :: Python :: 3 :: Only
Classifier: Programming Language :: Python :: 3.7
Classifier: Programming Language :: Python :: 3.8
Requires-Dist: httpx (==0.24.1)
Requires-Dist: prefect (>=2.11.5,<3.0.0)
Requires-Dist: pydantic (>=2.6.3,<3.0.0)
Project-URL: Repository, https://github.com/ultimatelife/prefect-supporter
